{
  "ticker": "CFG",
  "data_source": "yfinance",
  "revenue_cagr": 0.8,
  "years_analyzed": 4,
  "current": {
    "price": 60.86,
    "pe_ratio": 14.421802,
    "forward_pe": 9.519161,
    "market_cap_B": 25.7,
    "ev_ebitda": null,
    "price_to_fcf": null,
    "52w_high": 68.79,
    "52w_low": 38.796,
    "dividend_yield": 3.02,
    "sector": "Financial Services",
    "industry": "Banks - Regional",
    "beta": 1.041,
    "analyst_target": 73.14706,
    "recommendation": "strong_buy",
    "pct_from_52w_high": -11.5
  },
  "history": [
    {
      "year": "2025",
      "revenue_B": 8.2,
      "gross_margin": null,
      "operating_margin": null,
      "net_margin": 22.2,
      "fcf_margin": 24.7,
      "roic": 5.2,
      "debt_equity": 0.35
    },
    {
      "year": "2024",
      "revenue_B": 7.8,
      "gross_margin": null,
      "operating_margin": null,
      "net_margin": 19.3,
      "fcf_margin": 24.1,
      "roic": 4.4,
      "debt_equity": 0.43
    },
    {
      "year": "2023",
      "revenue_B": 8.2,
      "gross_margin": null,
      "operating_margin": null,
      "net_margin": 19.6,
      "fcf_margin": 33.9,
      "roic": 4.3,
      "debt_equity": 0.55
    },
    {
      "year": "2022",
      "revenue_B": 8.0,
      "gross_margin": null,
      "operating_margin": null,
      "net_margin": 25.8,
      "fcf_margin": 49.8,
      "roic": 5.2,
      "debt_equity": 0.67
    }
  ]
}