{
  "ticker": "VST",
  "data_source": "yfinance",
  "revenue_cagr": 8.9,
  "years_analyzed": 4,
  "current": {
    "price": 139.68,
    "pe_ratio": 23.357859,
    "forward_pe": 12.375451,
    "market_cap_B": 47.1,
    "ev_ebitda": 10.141,
    "price_to_fcf": null,
    "52w_high": 219.82,
    "52w_low": 137.81,
    "dividend_yield": 0.66,
    "sector": "Utilities",
    "industry": "Utilities - Independent Power Producers",
    "beta": 1.447,
    "analyst_target": 225.05882,
    "recommendation": "strong_buy",
    "pct_from_52w_high": -36.5
  },
  "history": [
    {
      "year": "2025",
      "revenue_B": 17.7,
      "gross_margin": 32.9,
      "operating_margin": 12.0,
      "net_margin": 5.3,
      "fcf_margin": 7.4,
      "roic": 4.5,
      "debt_equity": 3.11
    },
    {
      "year": "2024",
      "revenue_B": 17.2,
      "gross_margin": 43.7,
      "operating_margin": 23.7,
      "net_margin": 15.4,
      "fcf_margin": 14.4,
      "roic": 12.7,
      "debt_equity": 2.77
    },
    {
      "year": "2023",
      "revenue_B": 14.8,
      "gross_margin": 37.4,
      "operating_margin": 18.3,
      "net_margin": 10.1,
      "fcf_margin": 25.6,
      "roic": 8.6,
      "debt_equity": 2.28
    },
    {
      "year": "2022",
      "revenue_B": 13.7,
      "gross_margin": 12.3,
      "operating_margin": -8.0,
      "net_margin": -8.9,
      "fcf_margin": -5.9,
      "roic": -7.3,
      "debt_equity": 2.43
    }
  ]
}